wheel_doctor/__init__.py
wheel_doctor/__main__.py
wheel_doctor/wheel.py
wheel_doctor-0.1.0.dist-info/LICENSE
wheel_doctor-0.1.0.dist-info/METADATA
wheel_doctor-0.1.0.dist-info/WHEEL
wheel_doctor-0.1.0.dist-info/entry_points.txt
wheel_doctor-0.1.0.dist-info/RECORD
