Metadata-Version: 2.1
Name: wheel-doctor
Version: 0.1.0
Summary: 
License: MIT
Author: Lukas Bindreiter
Requires-Python: >=3.10,<4
Classifier: License :: OSI Approved :: MIT License
Classifier: Programming Language :: Python :: 3
Classifier: Programming Language :: Python :: 3.10
Classifier: Programming Language :: Python :: 3.11
Requires-Dist: tomli
Requires-Dist: tomli-w
Requires-Dist: typer[all]
